simple_pyirc/__init__.py
simple_pyirc/client.py
simple_pyirc/message.py
simple_pyirc-0.0.1.dist-info/METADATA
simple_pyirc-0.0.1.dist-info/RECORD
simple_pyirc-0.0.1.dist-info/WHEEL
simple_pyirc-0.0.1.dist-info/top_level.txt
