Metadata-Version: 2.1
Name: simple-pyirc
Version: 0.0.1
Summary: A light-weighted IRC client
Home-page: https://gitlab.com/MoaMoaK/simple-pyirc
Author: Maël Kervella
Author-email: dev@maelkervella.eu
License: UNKNOWN
Platform: UNKNOWN
Classifier: Development Status :: 4 - Beta
Classifier: Intended Audience :: Developers
Classifier: License :: OSI Approved :: MIT License
Classifier: Operating System :: OS Independent
Classifier: Programming Language :: Python :: 3
Classifier: Topic :: Communications :: Chat :: Internet Relay Chat
